stl_compressor/__init__.py
stl_compressor/stl_compressor_test.py
stl_compressor/stl_compressor_ui.py
stl_compressor-2.8.dist-info/LICENCE
stl_compressor-2.8.dist-info/METADATA
stl_compressor-2.8.dist-info/WHEEL
stl_compressor-2.8.dist-info/entry_points.txt
stl_compressor-2.8.dist-info/top_level.txt
stl_compressor-2.8.dist-info/RECORD
