Metadata-Version: 2.1
Name: stl-compressor
Version: 2.8
Summary: STL Compressor
Home-page: https://github.com/fan-ziqi/stl_compressor
Author: Ziqi Fan
Author-email: fanziqi614@gmail.com
License: Apache License 2.0
Platform: all
Classifier: Programming Language :: Python :: 3
Classifier: Operating System :: OS Independent
Requires-Dist: open3d
